[
  {
    "date": 1759375978,
    "date_readable": "2025-10-01 22:32:58",
    "timezone": "",
    "timezone_offset": "-0500",
    "hrv": 15.0,
    "unit": "ms",
    "source": "oura_ring_rmssd",
    "measurement_type": "rMSSD"
  },
  {
    "date": 1759376278,
    "date_readable": "2025-10-01 22:37:58",
    "timezone": "",
    "timezone_offset": "-0500",
    "hrv": 17.0,
    "unit": "ms",
    "source": "oura_ring_rmssd",
    "measurement_type": "rMSSD"
  },
  {
    "date": 1759376578,
    "date_readable": "2025-10-01 22:42:58",
    "timezone": "",
    "timezone_offset": "-0500",
    "hrv": 11.0,
    "unit": "ms",
    "source": "oura_ring_rmssd",
    "measurement_type": "rMSSD"
  },
  {
    "date": 1759376878,
    "date_readable": "2025-10-01 22:47:58",
    "timezone": "",
    "timezone_offset": "-0500",
    "hrv": 13.0,
    "unit": "ms",
    "source": "oura_ring_rmssd",
    "measurement_type": "rMSSD"
  },
  {
    "date": 1759377178,
    "date_readable": "2025-10-01 22:52:58",
    "timezone": "",
    "timezone_offset": "-0500",
    "hrv": 14.0,
    "unit": "ms",
    "source": "oura_ring_rmssd",
    "measurement_type": "rMSSD"
  },
  {
    "date": 1759377478,
    "date_readable": "2025-10-01 22:57:58",
    "timezone": "",
    "timezone_offset": "-0500",
    "hrv": 18.0,
    "unit": "ms",
    "source": "oura_ring_rmssd",
    "measurement_type": "rMSSD"
  },
  {
    "date": 1759377778,
    "date_readable": "2025-10-01 23:02:58",
    "timezone": "",
    "timezone_offset": "-0500",
    "hrv": 21.0,
    "unit": "ms",
    "source": "oura_ring_rmssd",
    "measurement_type": "rMSSD"
  },
  {
    "date": 1759378078,
    "date_readable": "2025-10-01 23:07:58",
    "timezone": "",
    "timezone_offset": "-0500",
    "hrv": 20.0,
    "unit": "ms",
    "source": "oura_ring_rmssd",
    "measurement_type": "rMSSD"
  },
  {
    "date": 1759378378,
    "date_readable": "2025-10-01 23:12:58",
    "timezone": "",
    "timezone_offset": "-0500",
    "hrv": 27.0,
    "unit": "ms",
    "source": "oura_ring_rmssd",
    "measurement_type": "rMSSD"
  },
  {
    "date": 1759378678,
    "date_readable": "2025-10-01 23:17:58",
    "timezone": "",
    "timezone_offset": "-0500",
    "hrv": 24.0,
    "unit": "ms",
    "source": "oura_ring_rmssd",
    "measurement_type": "rMSSD"
  },
  {
    "date": 1759378978,
    "date_readable": "2025-10-01 23:22:58",
    "timezone": "",
    "timezone_offset": "-0500",
    "hrv": 48.0,
    "unit": "ms",
    "source": "oura_ring_rmssd",
    "measurement_type": "rMSSD"
  },
  {
    "date": 1759379278,
    "date_readable": "2025-10-01 23:27:58",
    "timezone": "",
    "timezone_offset": "-0500",
    "hrv": 45.0,
    "unit": "ms",
    "source": "oura_ring_rmssd",
    "measurement_type": "rMSSD"
  },
  {
    "date": 1759379578,
    "date_readable": "2025-10-01 23:32:58",
    "timezone": "",
    "timezone_offset": "-0500",
    "hrv": 39.0,
    "unit": "ms",
    "source": "oura_ring_rmssd",
    "measurement_type": "rMSSD"
  },
  {
    "date": 1759379878,
    "date_readable": "2025-10-01 23:37:58",
    "timezone": "",
    "timezone_offset": "-0500",
    "hrv": 36.0,
    "unit": "ms",
    "source": "oura_ring_rmssd",
    "measurement_type": "rMSSD"
  },
  {
    "date": 1759380178,
    "date_readable": "2025-10-01 23:42:58",
    "timezone": "",
    "timezone_offset": "-0500",
    "hrv": 50.0,
    "unit": "ms",
    "source": "oura_ring_rmssd",
    "measurement_type": "rMSSD"
  },
  {
    "date": 1759380478,
    "date_readable": "2025-10-01 23:47:58",
    "timezone": "",
    "timezone_offset": "-0500",
    "hrv": 42.0,
    "unit": "ms",
    "source": "oura_ring_rmssd",
    "measurement_type": "rMSSD"
  },
  {
    "date": 1759380778,
    "date_readable": "2025-10-01 23:52:58",
    "timezone": "",
    "timezone_offset": "-0500",
    "hrv": 38.0,
    "unit": "ms",
    "source": "oura_ring_rmssd",
    "measurement_type": "rMSSD"
  },
  {
    "date": 1759381078,
    "date_readable": "2025-10-01 23:57:58",
    "timezone": "",
    "timezone_offset": "-0500",
    "hrv": 38.0,
    "unit": "ms",
    "source": "oura_ring_rmssd",
    "measurement_type": "rMSSD"
  },
  {
    "date": 1759381378,
    "date_readable": "2025-10-02 00:02:58",
    "timezone": "",
    "timezone_offset": "-0500",
    "hrv": 28.0,
    "unit": "ms",
    "source": "oura_ring_rmssd",
    "measurement_type": "rMSSD"
  },
  {
    "date": 1759381678,
    "date_readable": "2025-10-02 00:07:58",
    "timezone": "",
    "timezone_offset": "-0500",
    "hrv": 41.0,
    "unit": "ms",
    "source": "oura_ring_rmssd",
    "measurement_type": "rMSSD"
  },
  {
    "date": 1759381978,
    "date_readable": "2025-10-02 00:12:58",
    "timezone": "",
    "timezone_offset": "-0500",
    "hrv": 38.0,
    "unit": "ms",
    "source": "oura_ring_rmssd",
    "measurement_type": "rMSSD"
  },
  {
    "date": 1759382278,
    "date_readable": "2025-10-02 00:17:58",
    "timezone": "",
    "timezone_offset": "-0500",
    "hrv": 32.0,
    "unit": "ms",
    "source": "oura_ring_rmssd",
    "measurement_type": "rMSSD"
  },
  {
    "date": 1759382578,
    "date_readable": "2025-10-02 00:22:58",
    "timezone": "",
    "timezone_offset": "-0500",
    "hrv": 34.0,
    "unit": "ms",
    "source": "oura_ring_rmssd",
    "measurement_type": "rMSSD"
  },
  {
    "date": 1759382878,
    "date_readable": "2025-10-02 00:27:58",
    "timezone": "",
    "timezone_offset": "-0500",
    "hrv": 30.0,
    "unit": "ms",
    "source": "oura_ring_rmssd",
    "measurement_type": "rMSSD"
  },
  {
    "date": 1759383178,
    "date_readable": "2025-10-02 00:32:58",
    "timezone": "",
    "timezone_offset": "-0500",
    "hrv": 34.0,
    "unit": "ms",
    "source": "oura_ring_rmssd",
    "measurement_type": "rMSSD"
  },
  {
    "date": 1759383478,
    "date_readable": "2025-10-02 00:37:58",
    "timezone": "",
    "timezone_offset": "-0500",
    "hrv": 45.0,
    "unit": "ms",
    "source": "oura_ring_rmssd",
    "measurement_type": "rMSSD"
  },
  {
    "date": 1759383778,
    "date_readable": "2025-10-02 00:42:58",
    "timezone": "",
    "timezone_offset": "-0500",
    "hrv": 64.0,
    "unit": "ms",
    "source": "oura_ring_rmssd",
    "measurement_type": "rMSSD"
  },
  {
    "date": 1759384078,
    "date_readable": "2025-10-02 00:47:58",
    "timezone": "",
    "timezone_offset": "-0500",
    "hrv": 46.0,
    "unit": "ms",
    "source": "oura_ring_rmssd",
    "measurement_type": "rMSSD"
  },
  {
    "date": 1759384378,
    "date_readable": "2025-10-02 00:52:58",
    "timezone": "",
    "timezone_offset": "-0500",
    "hrv": 40.0,
    "unit": "ms",
    "source": "oura_ring_rmssd",
    "measurement_type": "rMSSD"
  },
  {
    "date": 1759384678,
    "date_readable": "2025-10-02 00:57:58",
    "timezone": "",
    "timezone_offset": "-0500",
    "hrv": 43.0,
    "unit": "ms",
    "source": "oura_ring_rmssd",
    "measurement_type": "rMSSD"
  },
  {
    "date": 1759384978,
    "date_readable": "2025-10-02 01:02:58",
    "timezone": "",
    "timezone_offset": "-0500",
    "hrv": 34.0,
    "unit": "ms",
    "source": "oura_ring_rmssd",
    "measurement_type": "rMSSD"
  },
  {
    "date": 1759385278,
    "date_readable": "2025-10-02 01:07:58",
    "timezone": "",
    "timezone_offset": "-0500",
    "hrv": 34.0,
    "unit": "ms",
    "source": "oura_ring_rmssd",
    "measurement_type": "rMSSD"
  },
  {
    "date": 1759385578,
    "date_readable": "2025-10-02 01:12:58",
    "timezone": "",
    "timezone_offset": "-0500",
    "hrv": 57.0,
    "unit": "ms",
    "source": "oura_ring_rmssd",
    "measurement_type": "rMSSD"
  },
  {
    "date": 1759385878,
    "date_readable": "2025-10-02 01:17:58",
    "timezone": "",
    "timezone_offset": "-0500",
    "hrv": 41.0,
    "unit": "ms",
    "source": "oura_ring_rmssd",
    "measurement_type": "rMSSD"
  },
  {
    "date": 1759386178,
    "date_readable": "2025-10-02 01:22:58",
    "timezone": "",
    "timezone_offset": "-0500",
    "hrv": 26.0,
    "unit": "ms",
    "source": "oura_ring_rmssd",
    "measurement_type": "rMSSD"
  },
  {
    "date": 1759386478,
    "date_readable": "2025-10-02 01:27:58",
    "timezone": "",
    "timezone_offset": "-0500",
    "hrv": 27.0,
    "unit": "ms",
    "source": "oura_ring_rmssd",
    "measurement_type": "rMSSD"
  },
  {
    "date": 1759386778,
    "date_readable": "2025-10-02 01:32:58",
    "timezone": "",
    "timezone_offset": "-0500",
    "hrv": 28.0,
    "unit": "ms",
    "source": "oura_ring_rmssd",
    "measurement_type": "rMSSD"
  },
  {
    "date": 1759387078,
    "date_readable": "2025-10-02 01:37:58",
    "timezone": "",
    "timezone_offset": "-0500",
    "hrv": 20.0,
    "unit": "ms",
    "source": "oura_ring_rmssd",
    "measurement_type": "rMSSD"
  },
  {
    "date": 1759387378,
    "date_readable": "2025-10-02 01:42:58",
    "timezone": "",
    "timezone_offset": "-0500",
    "hrv": 37.0,
    "unit": "ms",
    "source": "oura_ring_rmssd",
    "measurement_type": "rMSSD"
  },
  {
    "date": 1759387678,
    "date_readable": "2025-10-02 01:47:58",
    "timezone": "",
    "timezone_offset": "-0500",
    "hrv": 26.0,
    "unit": "ms",
    "source": "oura_ring_rmssd",
    "measurement_type": "rMSSD"
  },
  {
    "date": 1759387978,
    "date_readable": "2025-10-02 01:52:58",
    "timezone": "",
    "timezone_offset": "-0500",
    "hrv": 31.0,
    "unit": "ms",
    "source": "oura_ring_rmssd",
    "measurement_type": "rMSSD"
  },
  {
    "date": 1759388278,
    "date_readable": "2025-10-02 01:57:58",
    "timezone": "",
    "timezone_offset": "-0500",
    "hrv": 25.0,
    "unit": "ms",
    "source": "oura_ring_rmssd",
    "measurement_type": "rMSSD"
  },
  {
    "date": 1759388578,
    "date_readable": "2025-10-02 02:02:58",
    "timezone": "",
    "timezone_offset": "-0500",
    "hrv": 33.0,
    "unit": "ms",
    "source": "oura_ring_rmssd",
    "measurement_type": "rMSSD"
  },
  {
    "date": 1759388878,
    "date_readable": "2025-10-02 02:07:58",
    "timezone": "",
    "timezone_offset": "-0500",
    "hrv": 44.0,
    "unit": "ms",
    "source": "oura_ring_rmssd",
    "measurement_type": "rMSSD"
  },
  {
    "date": 1759389178,
    "date_readable": "2025-10-02 02:12:58",
    "timezone": "",
    "timezone_offset": "-0500",
    "hrv": 41.0,
    "unit": "ms",
    "source": "oura_ring_rmssd",
    "measurement_type": "rMSSD"
  },
  {
    "date": 1759389478,
    "date_readable": "2025-10-02 02:17:58",
    "timezone": "",
    "timezone_offset": "-0500",
    "hrv": 44.0,
    "unit": "ms",
    "source": "oura_ring_rmssd",
    "measurement_type": "rMSSD"
  },
  {
    "date": 1759389778,
    "date_readable": "2025-10-02 02:22:58",
    "timezone": "",
    "timezone_offset": "-0500",
    "hrv": 44.0,
    "unit": "ms",
    "source": "oura_ring_rmssd",
    "measurement_type": "rMSSD"
  },
  {
    "date": 1759390078,
    "date_readable": "2025-10-02 02:27:58",
    "timezone": "",
    "timezone_offset": "-0500",
    "hrv": 45.0,
    "unit": "ms",
    "source": "oura_ring_rmssd",
    "measurement_type": "rMSSD"
  },
  {
    "date": 1759390378,
    "date_readable": "2025-10-02 02:32:58",
    "timezone": "",
    "timezone_offset": "-0500",
    "hrv": 45.0,
    "unit": "ms",
    "source": "oura_ring_rmssd",
    "measurement_type": "rMSSD"
  },
  {
    "date": 1759390678,
    "date_readable": "2025-10-02 02:37:58",
    "timezone": "",
    "timezone_offset": "-0500",
    "hrv": 57.0,
    "unit": "ms",
    "source": "oura_ring_rmssd",
    "measurement_type": "rMSSD"
  },
  {
    "date": 1759390978,
    "date_readable": "2025-10-02 02:42:58",
    "timezone": "",
    "timezone_offset": "-0500",
    "hrv": 51.0,
    "unit": "ms",
    "source": "oura_ring_rmssd",
    "measurement_type": "rMSSD"
  },
  {
    "date": 1759391278,
    "date_readable": "2025-10-02 02:47:58",
    "timezone": "",
    "timezone_offset": "-0500",
    "hrv": 59.0,
    "unit": "ms",
    "source": "oura_ring_rmssd",
    "measurement_type": "rMSSD"
  },
  {
    "date": 1759391578,
    "date_readable": "2025-10-02 02:52:58",
    "timezone": "",
    "timezone_offset": "-0500",
    "hrv": 59.0,
    "unit": "ms",
    "source": "oura_ring_rmssd",
    "measurement_type": "rMSSD"
  },
  {
    "date": 1759391878,
    "date_readable": "2025-10-02 02:57:58",
    "timezone": "",
    "timezone_offset": "-0500",
    "hrv": 55.0,
    "unit": "ms",
    "source": "oura_ring_rmssd",
    "measurement_type": "rMSSD"
  },
  {
    "date": 1759392178,
    "date_readable": "2025-10-02 03:02:58",
    "timezone": "",
    "timezone_offset": "-0500",
    "hrv": 40.0,
    "unit": "ms",
    "source": "oura_ring_rmssd",
    "measurement_type": "rMSSD"
  },
  {
    "date": 1759392478,
    "date_readable": "2025-10-02 03:07:58",
    "timezone": "",
    "timezone_offset": "-0500",
    "hrv": 54.0,
    "unit": "ms",
    "source": "oura_ring_rmssd",
    "measurement_type": "rMSSD"
  },
  {
    "date": 1759392778,
    "date_readable": "2025-10-02 03:12:58",
    "timezone": "",
    "timezone_offset": "-0500",
    "hrv": 44.0,
    "unit": "ms",
    "source": "oura_ring_rmssd",
    "measurement_type": "rMSSD"
  },
  {
    "date": 1759393078,
    "date_readable": "2025-10-02 03:17:58",
    "timezone": "",
    "timezone_offset": "-0500",
    "hrv": 36.0,
    "unit": "ms",
    "source": "oura_ring_rmssd",
    "measurement_type": "rMSSD"
  },
  {
    "date": 1759393378,
    "date_readable": "2025-10-02 03:22:58",
    "timezone": "",
    "timezone_offset": "-0500",
    "hrv": 50.0,
    "unit": "ms",
    "source": "oura_ring_rmssd",
    "measurement_type": "rMSSD"
  },
  {
    "date": 1759393678,
    "date_readable": "2025-10-02 03:27:58",
    "timezone": "",
    "timezone_offset": "-0500",
    "hrv": 46.0,
    "unit": "ms",
    "source": "oura_ring_rmssd",
    "measurement_type": "rMSSD"
  },
  {
    "date": 1759393978,
    "date_readable": "2025-10-02 03:32:58",
    "timezone": "",
    "timezone_offset": "-0500",
    "hrv": 36.0,
    "unit": "ms",
    "source": "oura_ring_rmssd",
    "measurement_type": "rMSSD"
  },
  {
    "date": 1759394278,
    "date_readable": "2025-10-02 03:37:58",
    "timezone": "",
    "timezone_offset": "-0500",
    "hrv": 35.0,
    "unit": "ms",
    "source": "oura_ring_rmssd",
    "measurement_type": "rMSSD"
  },
  {
    "date": 1759394578,
    "date_readable": "2025-10-02 03:42:58",
    "timezone": "",
    "timezone_offset": "-0500",
    "hrv": 36.0,
    "unit": "ms",
    "source": "oura_ring_rmssd",
    "measurement_type": "rMSSD"
  },
  {
    "date": 1759394878,
    "date_readable": "2025-10-02 03:47:58",
    "timezone": "",
    "timezone_offset": "-0500",
    "hrv": 34.0,
    "unit": "ms",
    "source": "oura_ring_rmssd",
    "measurement_type": "rMSSD"
  },
  {
    "date": 1759395178,
    "date_readable": "2025-10-02 03:52:58",
    "timezone": "",
    "timezone_offset": "-0500",
    "hrv": 36.0,
    "unit": "ms",
    "source": "oura_ring_rmssd",
    "measurement_type": "rMSSD"
  },
  {
    "date": 1759395478,
    "date_readable": "2025-10-02 03:57:58",
    "timezone": "",
    "timezone_offset": "-0500",
    "hrv": 40.0,
    "unit": "ms",
    "source": "oura_ring_rmssd",
    "measurement_type": "rMSSD"
  },
  {
    "date": 1759395778,
    "date_readable": "2025-10-02 04:02:58",
    "timezone": "",
    "timezone_offset": "-0500",
    "hrv": 50.0,
    "unit": "ms",
    "source": "oura_ring_rmssd",
    "measurement_type": "rMSSD"
  },
  {
    "date": 1759396078,
    "date_readable": "2025-10-02 04:07:58",
    "timezone": "",
    "timezone_offset": "-0500",
    "hrv": 31.0,
    "unit": "ms",
    "source": "oura_ring_rmssd",
    "measurement_type": "rMSSD"
  },
  {
    "date": 1759396378,
    "date_readable": "2025-10-02 04:12:58",
    "timezone": "",
    "timezone_offset": "-0500",
    "hrv": 32.0,
    "unit": "ms",
    "source": "oura_ring_rmssd",
    "measurement_type": "rMSSD"
  },
  {
    "date": 1759396678,
    "date_readable": "2025-10-02 04:17:58",
    "timezone": "",
    "timezone_offset": "-0500",
    "hrv": 29.0,
    "unit": "ms",
    "source": "oura_ring_rmssd",
    "measurement_type": "rMSSD"
  },
  {
    "date": 1759396978,
    "date_readable": "2025-10-02 04:22:58",
    "timezone": "",
    "timezone_offset": "-0500",
    "hrv": 44.0,
    "unit": "ms",
    "source": "oura_ring_rmssd",
    "measurement_type": "rMSSD"
  },
  {
    "date": 1759397278,
    "date_readable": "2025-10-02 04:27:58",
    "timezone": "",
    "timezone_offset": "-0500",
    "hrv": 36.0,
    "unit": "ms",
    "source": "oura_ring_rmssd",
    "measurement_type": "rMSSD"
  },
  {
    "date": 1759397578,
    "date_readable": "2025-10-02 04:32:58",
    "timezone": "",
    "timezone_offset": "-0500",
    "hrv": 38.0,
    "unit": "ms",
    "source": "oura_ring_rmssd",
    "measurement_type": "rMSSD"
  },
  {
    "date": 1759397878,
    "date_readable": "2025-10-02 04:37:58",
    "timezone": "",
    "timezone_offset": "-0500",
    "hrv": 28.0,
    "unit": "ms",
    "source": "oura_ring_rmssd",
    "measurement_type": "rMSSD"
  },
  {
    "date": 1759398178,
    "date_readable": "2025-10-02 04:42:58",
    "timezone": "",
    "timezone_offset": "-0500",
    "hrv": 26.0,
    "unit": "ms",
    "source": "oura_ring_rmssd",
    "measurement_type": "rMSSD"
  },
  {
    "date": 1759398478,
    "date_readable": "2025-10-02 04:47:58",
    "timezone": "",
    "timezone_offset": "-0500",
    "hrv": 35.0,
    "unit": "ms",
    "source": "oura_ring_rmssd",
    "measurement_type": "rMSSD"
  },
  {
    "date": 1759398778,
    "date_readable": "2025-10-02 04:52:58",
    "timezone": "",
    "timezone_offset": "-0500",
    "hrv": 31.0,
    "unit": "ms",
    "source": "oura_ring_rmssd",
    "measurement_type": "rMSSD"
  },
  {
    "date": 1759399078,
    "date_readable": "2025-10-02 04:57:58",
    "timezone": "",
    "timezone_offset": "-0500",
    "hrv": 24.0,
    "unit": "ms",
    "source": "oura_ring_rmssd",
    "measurement_type": "rMSSD"
  },
  {
    "date": 1759399378,
    "date_readable": "2025-10-02 05:02:58",
    "timezone": "",
    "timezone_offset": "-0500",
    "hrv": 26.0,
    "unit": "ms",
    "source": "oura_ring_rmssd",
    "measurement_type": "rMSSD"
  },
  {
    "date": 1759399678,
    "date_readable": "2025-10-02 05:07:58",
    "timezone": "",
    "timezone_offset": "-0500",
    "hrv": 32.0,
    "unit": "ms",
    "source": "oura_ring_rmssd",
    "measurement_type": "rMSSD"
  },
  {
    "date": 1759399978,
    "date_readable": "2025-10-02 05:12:58",
    "timezone": "",
    "timezone_offset": "-0500",
    "hrv": 33.0,
    "unit": "ms",
    "source": "oura_ring_rmssd",
    "measurement_type": "rMSSD"
  },
  {
    "date": 1759400278,
    "date_readable": "2025-10-02 05:17:58",
    "timezone": "",
    "timezone_offset": "-0500",
    "hrv": 27.0,
    "unit": "ms",
    "source": "oura_ring_rmssd",
    "measurement_type": "rMSSD"
  },
  {
    "date": 1759400578,
    "date_readable": "2025-10-02 05:22:58",
    "timezone": "",
    "timezone_offset": "-0500",
    "hrv": 26.0,
    "unit": "ms",
    "source": "oura_ring_rmssd",
    "measurement_type": "rMSSD"
  },
  {
    "date": 1759400878,
    "date_readable": "2025-10-02 05:27:58",
    "timezone": "",
    "timezone_offset": "-0500",
    "hrv": 26.0,
    "unit": "ms",
    "source": "oura_ring_rmssd",
    "measurement_type": "rMSSD"
  },
  {
    "date": 1759401178,
    "date_readable": "2025-10-02 05:32:58",
    "timezone": "",
    "timezone_offset": "-0500",
    "hrv": 43.0,
    "unit": "ms",
    "source": "oura_ring_rmssd",
    "measurement_type": "rMSSD"
  },
  {
    "date": 1759401478,
    "date_readable": "2025-10-02 05:37:58",
    "timezone": "",
    "timezone_offset": "-0500",
    "hrv": 51.0,
    "unit": "ms",
    "source": "oura_ring_rmssd",
    "measurement_type": "rMSSD"
  },
  {
    "date": 1759401778,
    "date_readable": "2025-10-02 05:42:58",
    "timezone": "",
    "timezone_offset": "-0500",
    "hrv": 42.0,
    "unit": "ms",
    "source": "oura_ring_rmssd",
    "measurement_type": "rMSSD"
  },
  {
    "date": 1759402078,
    "date_readable": "2025-10-02 05:47:58",
    "timezone": "",
    "timezone_offset": "-0500",
    "hrv": 41.0,
    "unit": "ms",
    "source": "oura_ring_rmssd",
    "measurement_type": "rMSSD"
  },
  {
    "date": 1759402378,
    "date_readable": "2025-10-02 05:52:58",
    "timezone": "",
    "timezone_offset": "-0500",
    "hrv": 34.0,
    "unit": "ms",
    "source": "oura_ring_rmssd",
    "measurement_type": "rMSSD"
  },
  {
    "date": 1759402678,
    "date_readable": "2025-10-02 05:57:58",
    "timezone": "",
    "timezone_offset": "-0500",
    "hrv": 37.0,
    "unit": "ms",
    "source": "oura_ring_rmssd",
    "measurement_type": "rMSSD"
  },
  {
    "date": 1759402978,
    "date_readable": "2025-10-02 06:02:58",
    "timezone": "",
    "timezone_offset": "-0500",
    "hrv": 26.0,
    "unit": "ms",
    "source": "oura_ring_rmssd",
    "measurement_type": "rMSSD"
  },
  {
    "date": 1759403278,
    "date_readable": "2025-10-02 06:07:58",
    "timezone": "",
    "timezone_offset": "-0500",
    "hrv": 27.0,
    "unit": "ms",
    "source": "oura_ring_rmssd",
    "measurement_type": "rMSSD"
  },
  {
    "date": 1759403578,
    "date_readable": "2025-10-02 06:12:58",
    "timezone": "",
    "timezone_offset": "-0500",
    "hrv": 27.0,
    "unit": "ms",
    "source": "oura_ring_rmssd",
    "measurement_type": "rMSSD"
  },
  {
    "date": 1759403878,
    "date_readable": "2025-10-02 06:17:58",
    "timezone": "",
    "timezone_offset": "-0500",
    "hrv": 26.0,
    "unit": "ms",
    "source": "oura_ring_rmssd",
    "measurement_type": "rMSSD"
  },
  {
    "date": 1759404178,
    "date_readable": "2025-10-02 06:22:58",
    "timezone": "",
    "timezone_offset": "-0500",
    "hrv": 29.0,
    "unit": "ms",
    "source": "oura_ring_rmssd",
    "measurement_type": "rMSSD"
  },
  {
    "date": 1759404478,
    "date_readable": "2025-10-02 06:27:58",
    "timezone": "",
    "timezone_offset": "-0500",
    "hrv": 41.0,
    "unit": "ms",
    "source": "oura_ring_rmssd",
    "measurement_type": "rMSSD"
  }
]