[
  {
    "date": 1774239151,
    "date_readable": "2026-03-22 23:12:31",
    "timezone": "UTC-05:00",
    "timezone_offset": "-0500",
    "hrv": 12.0,
    "unit": "ms",
    "source": "oura_ring_rmssd",
    "measurement_type": "rMSSD"
  },
  {
    "date": 1774239451,
    "date_readable": "2026-03-22 23:17:31",
    "timezone": "UTC-05:00",
    "timezone_offset": "-0500",
    "hrv": 29.0,
    "unit": "ms",
    "source": "oura_ring_rmssd",
    "measurement_type": "rMSSD"
  },
  {
    "date": 1774239751,
    "date_readable": "2026-03-22 23:22:31",
    "timezone": "UTC-05:00",
    "timezone_offset": "-0500",
    "hrv": 41.0,
    "unit": "ms",
    "source": "oura_ring_rmssd",
    "measurement_type": "rMSSD"
  },
  {
    "date": 1774240051,
    "date_readable": "2026-03-22 23:27:31",
    "timezone": "UTC-05:00",
    "timezone_offset": "-0500",
    "hrv": 27.0,
    "unit": "ms",
    "source": "oura_ring_rmssd",
    "measurement_type": "rMSSD"
  },
  {
    "date": 1774240351,
    "date_readable": "2026-03-22 23:32:31",
    "timezone": "UTC-05:00",
    "timezone_offset": "-0500",
    "hrv": 31.0,
    "unit": "ms",
    "source": "oura_ring_rmssd",
    "measurement_type": "rMSSD"
  },
  {
    "date": 1774240651,
    "date_readable": "2026-03-22 23:37:31",
    "timezone": "UTC-05:00",
    "timezone_offset": "-0500",
    "hrv": 27.0,
    "unit": "ms",
    "source": "oura_ring_rmssd",
    "measurement_type": "rMSSD"
  },
  {
    "date": 1774240951,
    "date_readable": "2026-03-22 23:42:31",
    "timezone": "UTC-05:00",
    "timezone_offset": "-0500",
    "hrv": 27.0,
    "unit": "ms",
    "source": "oura_ring_rmssd",
    "measurement_type": "rMSSD"
  },
  {
    "date": 1774241251,
    "date_readable": "2026-03-22 23:47:31",
    "timezone": "UTC-05:00",
    "timezone_offset": "-0500",
    "hrv": 21.0,
    "unit": "ms",
    "source": "oura_ring_rmssd",
    "measurement_type": "rMSSD"
  },
  {
    "date": 1774241551,
    "date_readable": "2026-03-22 23:52:31",
    "timezone": "UTC-05:00",
    "timezone_offset": "-0500",
    "hrv": 16.0,
    "unit": "ms",
    "source": "oura_ring_rmssd",
    "measurement_type": "rMSSD"
  },
  {
    "date": 1774241851,
    "date_readable": "2026-03-22 23:57:31",
    "timezone": "UTC-05:00",
    "timezone_offset": "-0500",
    "hrv": 16.0,
    "unit": "ms",
    "source": "oura_ring_rmssd",
    "measurement_type": "rMSSD"
  },
  {
    "date": 1774242151,
    "date_readable": "2026-03-23 00:02:31",
    "timezone": "UTC-05:00",
    "timezone_offset": "-0500",
    "hrv": 18.0,
    "unit": "ms",
    "source": "oura_ring_rmssd",
    "measurement_type": "rMSSD"
  },
  {
    "date": 1774242451,
    "date_readable": "2026-03-23 00:07:31",
    "timezone": "UTC-05:00",
    "timezone_offset": "-0500",
    "hrv": 31.0,
    "unit": "ms",
    "source": "oura_ring_rmssd",
    "measurement_type": "rMSSD"
  },
  {
    "date": 1774242751,
    "date_readable": "2026-03-23 00:12:31",
    "timezone": "UTC-05:00",
    "timezone_offset": "-0500",
    "hrv": 21.0,
    "unit": "ms",
    "source": "oura_ring_rmssd",
    "measurement_type": "rMSSD"
  },
  {
    "date": 1774243051,
    "date_readable": "2026-03-23 00:17:31",
    "timezone": "UTC-05:00",
    "timezone_offset": "-0500",
    "hrv": 12.0,
    "unit": "ms",
    "source": "oura_ring_rmssd",
    "measurement_type": "rMSSD"
  },
  {
    "date": 1774243351,
    "date_readable": "2026-03-23 00:22:31",
    "timezone": "UTC-05:00",
    "timezone_offset": "-0500",
    "hrv": 20.0,
    "unit": "ms",
    "source": "oura_ring_rmssd",
    "measurement_type": "rMSSD"
  },
  {
    "date": 1774243651,
    "date_readable": "2026-03-23 00:27:31",
    "timezone": "UTC-05:00",
    "timezone_offset": "-0500",
    "hrv": 20.0,
    "unit": "ms",
    "source": "oura_ring_rmssd",
    "measurement_type": "rMSSD"
  },
  {
    "date": 1774243951,
    "date_readable": "2026-03-23 00:32:31",
    "timezone": "UTC-05:00",
    "timezone_offset": "-0500",
    "hrv": 17.0,
    "unit": "ms",
    "source": "oura_ring_rmssd",
    "measurement_type": "rMSSD"
  },
  {
    "date": 1774244251,
    "date_readable": "2026-03-23 00:37:31",
    "timezone": "UTC-05:00",
    "timezone_offset": "-0500",
    "hrv": 16.0,
    "unit": "ms",
    "source": "oura_ring_rmssd",
    "measurement_type": "rMSSD"
  },
  {
    "date": 1774244551,
    "date_readable": "2026-03-23 00:42:31",
    "timezone": "UTC-05:00",
    "timezone_offset": "-0500",
    "hrv": 20.0,
    "unit": "ms",
    "source": "oura_ring_rmssd",
    "measurement_type": "rMSSD"
  },
  {
    "date": 1774244851,
    "date_readable": "2026-03-23 00:47:31",
    "timezone": "UTC-05:00",
    "timezone_offset": "-0500",
    "hrv": 23.0,
    "unit": "ms",
    "source": "oura_ring_rmssd",
    "measurement_type": "rMSSD"
  },
  {
    "date": 1774245151,
    "date_readable": "2026-03-23 00:52:31",
    "timezone": "UTC-05:00",
    "timezone_offset": "-0500",
    "hrv": 27.0,
    "unit": "ms",
    "source": "oura_ring_rmssd",
    "measurement_type": "rMSSD"
  },
  {
    "date": 1774245451,
    "date_readable": "2026-03-23 00:57:31",
    "timezone": "UTC-05:00",
    "timezone_offset": "-0500",
    "hrv": 24.0,
    "unit": "ms",
    "source": "oura_ring_rmssd",
    "measurement_type": "rMSSD"
  },
  {
    "date": 1774245751,
    "date_readable": "2026-03-23 01:02:31",
    "timezone": "UTC-05:00",
    "timezone_offset": "-0500",
    "hrv": 22.0,
    "unit": "ms",
    "source": "oura_ring_rmssd",
    "measurement_type": "rMSSD"
  },
  {
    "date": 1774246051,
    "date_readable": "2026-03-23 01:07:31",
    "timezone": "UTC-05:00",
    "timezone_offset": "-0500",
    "hrv": 10.0,
    "unit": "ms",
    "source": "oura_ring_rmssd",
    "measurement_type": "rMSSD"
  },
  {
    "date": 1774246351,
    "date_readable": "2026-03-23 01:12:31",
    "timezone": "UTC-05:00",
    "timezone_offset": "-0500",
    "hrv": 23.0,
    "unit": "ms",
    "source": "oura_ring_rmssd",
    "measurement_type": "rMSSD"
  },
  {
    "date": 1774246651,
    "date_readable": "2026-03-23 01:17:31",
    "timezone": "UTC-05:00",
    "timezone_offset": "-0500",
    "hrv": 13.0,
    "unit": "ms",
    "source": "oura_ring_rmssd",
    "measurement_type": "rMSSD"
  },
  {
    "date": 1774246951,
    "date_readable": "2026-03-23 01:22:31",
    "timezone": "UTC-05:00",
    "timezone_offset": "-0500",
    "hrv": 15.0,
    "unit": "ms",
    "source": "oura_ring_rmssd",
    "measurement_type": "rMSSD"
  },
  {
    "date": 1774247251,
    "date_readable": "2026-03-23 01:27:31",
    "timezone": "UTC-05:00",
    "timezone_offset": "-0500",
    "hrv": 24.0,
    "unit": "ms",
    "source": "oura_ring_rmssd",
    "measurement_type": "rMSSD"
  },
  {
    "date": 1774247551,
    "date_readable": "2026-03-23 01:32:31",
    "timezone": "UTC-05:00",
    "timezone_offset": "-0500",
    "hrv": 34.0,
    "unit": "ms",
    "source": "oura_ring_rmssd",
    "measurement_type": "rMSSD"
  },
  {
    "date": 1774247851,
    "date_readable": "2026-03-23 01:37:31",
    "timezone": "UTC-05:00",
    "timezone_offset": "-0500",
    "hrv": 30.0,
    "unit": "ms",
    "source": "oura_ring_rmssd",
    "measurement_type": "rMSSD"
  },
  {
    "date": 1774248151,
    "date_readable": "2026-03-23 01:42:31",
    "timezone": "UTC-05:00",
    "timezone_offset": "-0500",
    "hrv": 32.0,
    "unit": "ms",
    "source": "oura_ring_rmssd",
    "measurement_type": "rMSSD"
  },
  {
    "date": 1774248451,
    "date_readable": "2026-03-23 01:47:31",
    "timezone": "UTC-05:00",
    "timezone_offset": "-0500",
    "hrv": 26.0,
    "unit": "ms",
    "source": "oura_ring_rmssd",
    "measurement_type": "rMSSD"
  },
  {
    "date": 1774248751,
    "date_readable": "2026-03-23 01:52:31",
    "timezone": "UTC-05:00",
    "timezone_offset": "-0500",
    "hrv": 37.0,
    "unit": "ms",
    "source": "oura_ring_rmssd",
    "measurement_type": "rMSSD"
  },
  {
    "date": 1774249051,
    "date_readable": "2026-03-23 01:57:31",
    "timezone": "UTC-05:00",
    "timezone_offset": "-0500",
    "hrv": 19.0,
    "unit": "ms",
    "source": "oura_ring_rmssd",
    "measurement_type": "rMSSD"
  },
  {
    "date": 1774249351,
    "date_readable": "2026-03-23 02:02:31",
    "timezone": "UTC-05:00",
    "timezone_offset": "-0500",
    "hrv": 28.0,
    "unit": "ms",
    "source": "oura_ring_rmssd",
    "measurement_type": "rMSSD"
  },
  {
    "date": 1774249651,
    "date_readable": "2026-03-23 02:07:31",
    "timezone": "UTC-05:00",
    "timezone_offset": "-0500",
    "hrv": 25.0,
    "unit": "ms",
    "source": "oura_ring_rmssd",
    "measurement_type": "rMSSD"
  },
  {
    "date": 1774249951,
    "date_readable": "2026-03-23 02:12:31",
    "timezone": "UTC-05:00",
    "timezone_offset": "-0500",
    "hrv": 15.0,
    "unit": "ms",
    "source": "oura_ring_rmssd",
    "measurement_type": "rMSSD"
  },
  {
    "date": 1774250251,
    "date_readable": "2026-03-23 02:17:31",
    "timezone": "UTC-05:00",
    "timezone_offset": "-0500",
    "hrv": 22.0,
    "unit": "ms",
    "source": "oura_ring_rmssd",
    "measurement_type": "rMSSD"
  },
  {
    "date": 1774250551,
    "date_readable": "2026-03-23 02:22:31",
    "timezone": "UTC-05:00",
    "timezone_offset": "-0500",
    "hrv": 27.0,
    "unit": "ms",
    "source": "oura_ring_rmssd",
    "measurement_type": "rMSSD"
  },
  {
    "date": 1774250851,
    "date_readable": "2026-03-23 02:27:31",
    "timezone": "UTC-05:00",
    "timezone_offset": "-0500",
    "hrv": 19.0,
    "unit": "ms",
    "source": "oura_ring_rmssd",
    "measurement_type": "rMSSD"
  },
  {
    "date": 1774251151,
    "date_readable": "2026-03-23 02:32:31",
    "timezone": "UTC-05:00",
    "timezone_offset": "-0500",
    "hrv": 15.0,
    "unit": "ms",
    "source": "oura_ring_rmssd",
    "measurement_type": "rMSSD"
  },
  {
    "date": 1774251451,
    "date_readable": "2026-03-23 02:37:31",
    "timezone": "UTC-05:00",
    "timezone_offset": "-0500",
    "hrv": 20.0,
    "unit": "ms",
    "source": "oura_ring_rmssd",
    "measurement_type": "rMSSD"
  },
  {
    "date": 1774251751,
    "date_readable": "2026-03-23 02:42:31",
    "timezone": "UTC-05:00",
    "timezone_offset": "-0500",
    "hrv": 22.0,
    "unit": "ms",
    "source": "oura_ring_rmssd",
    "measurement_type": "rMSSD"
  },
  {
    "date": 1774252051,
    "date_readable": "2026-03-23 02:47:31",
    "timezone": "UTC-05:00",
    "timezone_offset": "-0500",
    "hrv": 18.0,
    "unit": "ms",
    "source": "oura_ring_rmssd",
    "measurement_type": "rMSSD"
  },
  {
    "date": 1774252351,
    "date_readable": "2026-03-23 02:52:31",
    "timezone": "UTC-05:00",
    "timezone_offset": "-0500",
    "hrv": 17.0,
    "unit": "ms",
    "source": "oura_ring_rmssd",
    "measurement_type": "rMSSD"
  },
  {
    "date": 1774252651,
    "date_readable": "2026-03-23 02:57:31",
    "timezone": "UTC-05:00",
    "timezone_offset": "-0500",
    "hrv": 19.0,
    "unit": "ms",
    "source": "oura_ring_rmssd",
    "measurement_type": "rMSSD"
  },
  {
    "date": 1774252951,
    "date_readable": "2026-03-23 03:02:31",
    "timezone": "UTC-05:00",
    "timezone_offset": "-0500",
    "hrv": 20.0,
    "unit": "ms",
    "source": "oura_ring_rmssd",
    "measurement_type": "rMSSD"
  },
  {
    "date": 1774253251,
    "date_readable": "2026-03-23 03:07:31",
    "timezone": "UTC-05:00",
    "timezone_offset": "-0500",
    "hrv": 28.0,
    "unit": "ms",
    "source": "oura_ring_rmssd",
    "measurement_type": "rMSSD"
  },
  {
    "date": 1774253551,
    "date_readable": "2026-03-23 03:12:31",
    "timezone": "UTC-05:00",
    "timezone_offset": "-0500",
    "hrv": 19.0,
    "unit": "ms",
    "source": "oura_ring_rmssd",
    "measurement_type": "rMSSD"
  },
  {
    "date": 1774253851,
    "date_readable": "2026-03-23 03:17:31",
    "timezone": "UTC-05:00",
    "timezone_offset": "-0500",
    "hrv": 22.0,
    "unit": "ms",
    "source": "oura_ring_rmssd",
    "measurement_type": "rMSSD"
  },
  {
    "date": 1774254151,
    "date_readable": "2026-03-23 03:22:31",
    "timezone": "UTC-05:00",
    "timezone_offset": "-0500",
    "hrv": 19.0,
    "unit": "ms",
    "source": "oura_ring_rmssd",
    "measurement_type": "rMSSD"
  },
  {
    "date": 1774254451,
    "date_readable": "2026-03-23 03:27:31",
    "timezone": "UTC-05:00",
    "timezone_offset": "-0500",
    "hrv": 17.0,
    "unit": "ms",
    "source": "oura_ring_rmssd",
    "measurement_type": "rMSSD"
  },
  {
    "date": 1774254751,
    "date_readable": "2026-03-23 03:32:31",
    "timezone": "UTC-05:00",
    "timezone_offset": "-0500",
    "hrv": 23.0,
    "unit": "ms",
    "source": "oura_ring_rmssd",
    "measurement_type": "rMSSD"
  },
  {
    "date": 1774255051,
    "date_readable": "2026-03-23 03:37:31",
    "timezone": "UTC-05:00",
    "timezone_offset": "-0500",
    "hrv": 21.0,
    "unit": "ms",
    "source": "oura_ring_rmssd",
    "measurement_type": "rMSSD"
  },
  {
    "date": 1774255351,
    "date_readable": "2026-03-23 03:42:31",
    "timezone": "UTC-05:00",
    "timezone_offset": "-0500",
    "hrv": 19.0,
    "unit": "ms",
    "source": "oura_ring_rmssd",
    "measurement_type": "rMSSD"
  },
  {
    "date": 1774255651,
    "date_readable": "2026-03-23 03:47:31",
    "timezone": "UTC-05:00",
    "timezone_offset": "-0500",
    "hrv": 15.0,
    "unit": "ms",
    "source": "oura_ring_rmssd",
    "measurement_type": "rMSSD"
  },
  {
    "date": 1774255951,
    "date_readable": "2026-03-23 03:52:31",
    "timezone": "UTC-05:00",
    "timezone_offset": "-0500",
    "hrv": 22.0,
    "unit": "ms",
    "source": "oura_ring_rmssd",
    "measurement_type": "rMSSD"
  },
  {
    "date": 1774256251,
    "date_readable": "2026-03-23 03:57:31",
    "timezone": "UTC-05:00",
    "timezone_offset": "-0500",
    "hrv": 13.0,
    "unit": "ms",
    "source": "oura_ring_rmssd",
    "measurement_type": "rMSSD"
  },
  {
    "date": 1774256551,
    "date_readable": "2026-03-23 04:02:31",
    "timezone": "UTC-05:00",
    "timezone_offset": "-0500",
    "hrv": 18.0,
    "unit": "ms",
    "source": "oura_ring_rmssd",
    "measurement_type": "rMSSD"
  },
  {
    "date": 1774256851,
    "date_readable": "2026-03-23 04:07:31",
    "timezone": "UTC-05:00",
    "timezone_offset": "-0500",
    "hrv": 15.0,
    "unit": "ms",
    "source": "oura_ring_rmssd",
    "measurement_type": "rMSSD"
  },
  {
    "date": 1774257151,
    "date_readable": "2026-03-23 04:12:31",
    "timezone": "UTC-05:00",
    "timezone_offset": "-0500",
    "hrv": 16.0,
    "unit": "ms",
    "source": "oura_ring_rmssd",
    "measurement_type": "rMSSD"
  },
  {
    "date": 1774257451,
    "date_readable": "2026-03-23 04:17:31",
    "timezone": "UTC-05:00",
    "timezone_offset": "-0500",
    "hrv": 19.0,
    "unit": "ms",
    "source": "oura_ring_rmssd",
    "measurement_type": "rMSSD"
  },
  {
    "date": 1774257751,
    "date_readable": "2026-03-23 04:22:31",
    "timezone": "UTC-05:00",
    "timezone_offset": "-0500",
    "hrv": 16.0,
    "unit": "ms",
    "source": "oura_ring_rmssd",
    "measurement_type": "rMSSD"
  },
  {
    "date": 1774258051,
    "date_readable": "2026-03-23 04:27:31",
    "timezone": "UTC-05:00",
    "timezone_offset": "-0500",
    "hrv": 24.0,
    "unit": "ms",
    "source": "oura_ring_rmssd",
    "measurement_type": "rMSSD"
  },
  {
    "date": 1774258351,
    "date_readable": "2026-03-23 04:32:31",
    "timezone": "UTC-05:00",
    "timezone_offset": "-0500",
    "hrv": 19.0,
    "unit": "ms",
    "source": "oura_ring_rmssd",
    "measurement_type": "rMSSD"
  },
  {
    "date": 1774258651,
    "date_readable": "2026-03-23 04:37:31",
    "timezone": "UTC-05:00",
    "timezone_offset": "-0500",
    "hrv": 18.0,
    "unit": "ms",
    "source": "oura_ring_rmssd",
    "measurement_type": "rMSSD"
  },
  {
    "date": 1774258951,
    "date_readable": "2026-03-23 04:42:31",
    "timezone": "UTC-05:00",
    "timezone_offset": "-0500",
    "hrv": 23.0,
    "unit": "ms",
    "source": "oura_ring_rmssd",
    "measurement_type": "rMSSD"
  },
  {
    "date": 1774259251,
    "date_readable": "2026-03-23 04:47:31",
    "timezone": "UTC-05:00",
    "timezone_offset": "-0500",
    "hrv": 18.0,
    "unit": "ms",
    "source": "oura_ring_rmssd",
    "measurement_type": "rMSSD"
  },
  {
    "date": 1774259551,
    "date_readable": "2026-03-23 04:52:31",
    "timezone": "UTC-05:00",
    "timezone_offset": "-0500",
    "hrv": 15.0,
    "unit": "ms",
    "source": "oura_ring_rmssd",
    "measurement_type": "rMSSD"
  },
  {
    "date": 1774259851,
    "date_readable": "2026-03-23 04:57:31",
    "timezone": "UTC-05:00",
    "timezone_offset": "-0500",
    "hrv": 18.0,
    "unit": "ms",
    "source": "oura_ring_rmssd",
    "measurement_type": "rMSSD"
  },
  {
    "date": 1774260151,
    "date_readable": "2026-03-23 05:02:31",
    "timezone": "UTC-05:00",
    "timezone_offset": "-0500",
    "hrv": 23.0,
    "unit": "ms",
    "source": "oura_ring_rmssd",
    "measurement_type": "rMSSD"
  },
  {
    "date": 1774260451,
    "date_readable": "2026-03-23 05:07:31",
    "timezone": "UTC-05:00",
    "timezone_offset": "-0500",
    "hrv": 26.0,
    "unit": "ms",
    "source": "oura_ring_rmssd",
    "measurement_type": "rMSSD"
  },
  {
    "date": 1774260751,
    "date_readable": "2026-03-23 05:12:31",
    "timezone": "UTC-05:00",
    "timezone_offset": "-0500",
    "hrv": 32.0,
    "unit": "ms",
    "source": "oura_ring_rmssd",
    "measurement_type": "rMSSD"
  },
  {
    "date": 1774261051,
    "date_readable": "2026-03-23 05:17:31",
    "timezone": "UTC-05:00",
    "timezone_offset": "-0500",
    "hrv": 24.0,
    "unit": "ms",
    "source": "oura_ring_rmssd",
    "measurement_type": "rMSSD"
  },
  {
    "date": 1774261351,
    "date_readable": "2026-03-23 05:22:31",
    "timezone": "UTC-05:00",
    "timezone_offset": "-0500",
    "hrv": 30.0,
    "unit": "ms",
    "source": "oura_ring_rmssd",
    "measurement_type": "rMSSD"
  },
  {
    "date": 1774261651,
    "date_readable": "2026-03-23 05:27:31",
    "timezone": "UTC-05:00",
    "timezone_offset": "-0500",
    "hrv": 19.0,
    "unit": "ms",
    "source": "oura_ring_rmssd",
    "measurement_type": "rMSSD"
  },
  {
    "date": 1774261951,
    "date_readable": "2026-03-23 05:32:31",
    "timezone": "UTC-05:00",
    "timezone_offset": "-0500",
    "hrv": 23.0,
    "unit": "ms",
    "source": "oura_ring_rmssd",
    "measurement_type": "rMSSD"
  },
  {
    "date": 1774262251,
    "date_readable": "2026-03-23 05:37:31",
    "timezone": "UTC-05:00",
    "timezone_offset": "-0500",
    "hrv": 15.0,
    "unit": "ms",
    "source": "oura_ring_rmssd",
    "measurement_type": "rMSSD"
  },
  {
    "date": 1774262551,
    "date_readable": "2026-03-23 05:42:31",
    "timezone": "UTC-05:00",
    "timezone_offset": "-0500",
    "hrv": 13.0,
    "unit": "ms",
    "source": "oura_ring_rmssd",
    "measurement_type": "rMSSD"
  },
  {
    "date": 1774262851,
    "date_readable": "2026-03-23 05:47:31",
    "timezone": "UTC-05:00",
    "timezone_offset": "-0500",
    "hrv": 13.0,
    "unit": "ms",
    "source": "oura_ring_rmssd",
    "measurement_type": "rMSSD"
  },
  {
    "date": 1774263151,
    "date_readable": "2026-03-23 05:52:31",
    "timezone": "UTC-05:00",
    "timezone_offset": "-0500",
    "hrv": 15.0,
    "unit": "ms",
    "source": "oura_ring_rmssd",
    "measurement_type": "rMSSD"
  },
  {
    "date": 1774263451,
    "date_readable": "2026-03-23 05:57:31",
    "timezone": "UTC-05:00",
    "timezone_offset": "-0500",
    "hrv": 15.0,
    "unit": "ms",
    "source": "oura_ring_rmssd",
    "measurement_type": "rMSSD"
  },
  {
    "date": 1774263751,
    "date_readable": "2026-03-23 06:02:31",
    "timezone": "UTC-05:00",
    "timezone_offset": "-0500",
    "hrv": 14.0,
    "unit": "ms",
    "source": "oura_ring_rmssd",
    "measurement_type": "rMSSD"
  },
  {
    "date": 1774264051,
    "date_readable": "2026-03-23 06:07:31",
    "timezone": "UTC-05:00",
    "timezone_offset": "-0500",
    "hrv": 15.0,
    "unit": "ms",
    "source": "oura_ring_rmssd",
    "measurement_type": "rMSSD"
  }
]